{
  "batch_id": "batch_008",
  "annotator": "expert_scholar",
  "annotated_at": "2025-12-21T09:43:14.821538",
  "ayat_count": 50,
  "annotations": [
    {
      "span_id": "QBM_10231",
      "reference": {
        "surah": 35,
        "ayah": 31,
        "surah_name": "فاطر"
      },
      "text_ar": "وَٱلَّذِىٓ أَوْحَيْنَآ إِلَيْكَ مِنَ ٱلْكِتَـٰبِ هُوَ ٱلْحَقُّ مُصَدِّقًا لِّمَا بَيْنَ يَدَيْهِ ۗ إِنَّ ٱللَّهَ بِعِبَادِهِۦ لَخَبِيرٌۢ بَصِيرٌ",
      "behavior_form": "relational_act",
      "agent": {
        "type": "AGT_ALLAH",
        "explicit": true
      },
      "normative": {
        "speech_mode": "informative",
        "evaluation": "neutral",
        "deontic_signal": "khabar"
      },
      "action": {
        "class": "ACT_VOLITIONAL",
        "textual_eval": "EVAL_NEUTRAL"
      },
      "axes": {
        "situational": "internal",
        "systemic": "SYS_GOD"
      },
      "evidence": {
        "support_type": "inferred"
      },
      "annotator": "expert_scholar",
      "annotated_at": "2025-12-21T09:43:14.816443"
    },
    {
      "span_id": "QBM_10232",
      "reference": {
        "surah": 35,
        "ayah": 32,
        "surah_name": "فاطر"
      },
      "text_ar": "ثُمَّ أَوْرَثْنَا ٱلْكِتَـٰبَ ٱلَّذِينَ ٱصْطَفَيْنَا مِنْ عِبَادِنَا ۖ فَمِنْهُمْ ظَالِمٌ لِّنَفْسِهِۦ وَمِنْهُم مُّقْتَصِدٌ وَمِنْهُمْ سَابِقٌۢ بِٱلْخَيْرَٰتِ بِإِذْنِ ٱللَّهِ ۚ ذَٰلِكَ هُوَ ٱلْفَضْلُ ٱلْكَبِيرُ",
      "behavior_form": "inner_state",
      "agent": {
        "type": "AGT_ALLAH",
        "explicit": true
      },
      "normative": {
        "speech_mode": "informative",
        "evaluation": "praise",
        "deontic_signal": "targhib"
      },
      "action": {
        "class": "ACT_PSYCHOLOGICAL",
        "textual_eval": "EVAL_SALIH"
      },
      "axes": {
        "situational": "internal",
        "systemic": "SYS_GOD"
      },
      "evidence": {
        "support_type": "inferred"
      },
      "annotator": "expert_scholar",
      "annotated_at": "2025-12-21T09:43:14.816443"
    },
    {
      "span_id": "QBM_10233",
      "reference": {
        "surah": 35,
        "ayah": 33,
        "surah_name": "فاطر"
      },
      "text_ar": "جَنَّـٰتُ عَدْنٍ يَدْخُلُونَهَا يُحَلَّوْنَ فِيهَا مِنْ أَسَاوِرَ مِن ذَهَبٍ وَلُؤْلُؤًا ۖ وَلِبَاسُهُمْ فِيهَا حَرِيرٌ",
      "behavior_form": "inner_state",
      "agent": {
        "type": "AGT_HUMAN_GENERAL",
        "explicit": false
      },
      "normative": {
        "speech_mode": "informative",
        "evaluation": "neutral",
        "deontic_signal": "khabar"
      },
      "action": {
        "class": "ACT_PSYCHOLOGICAL",
        "textual_eval": "EVAL_NEUTRAL"
      },
      "axes": {
        "situational": "internal",
        "systemic": "SYS_SOCIAL"
      },
      "evidence": {
        "support_type": "inferred"
      },
      "annotator": "expert_scholar",
      "annotated_at": "2025-12-21T09:43:14.816443"
    },
    {
      "span_id": "QBM_10234",
      "reference": {
        "surah": 35,
        "ayah": 34,
        "surah_name": "فاطر"
      },
      "text_ar": "وَقَالُوا۟ ٱلْحَمْدُ لِلَّهِ ٱلَّذِىٓ أَذْهَبَ عَنَّا ٱلْحَزَنَ ۖ إِنَّ رَبَّنَا لَغَفُورٌ شَكُورٌ",
      "behavior_form": "speech_act",
      "agent": {
        "type": "AGT_ALLAH",
        "explicit": true
      },
      "normative": {
        "speech_mode": "informative",
        "evaluation": "neutral",
        "deontic_signal": "khabar"
      },
      "action": {
        "class": "ACT_VOLITIONAL",
        "textual_eval": "EVAL_NEUTRAL"
      },
      "axes": {
        "situational": "external",
        "systemic": "SYS_GOD"
      },
      "evidence": {
        "support_type": "direct"
      },
      "annotator": "expert_scholar",
      "annotated_at": "2025-12-21T09:43:14.816443"
    },
    {
      "span_id": "QBM_10235",
      "reference": {
        "surah": 35,
        "ayah": 35,
        "surah_name": "فاطر"
      },
      "text_ar": "ٱلَّذِىٓ أَحَلَّنَا دَارَ ٱلْمُقَامَةِ مِن فَضْلِهِۦ لَا يَمَسُّنَا فِيهَا نَصَبٌ وَلَا يَمَسُّنَا فِيهَا لُغُوبٌ",
      "behavior_form": "physical_act",
      "agent": {
        "type": "AGT_BELIEVER",
        "explicit": false
      },
      "normative": {
        "speech_mode": "interrogative",
        "evaluation": "neutral",
        "deontic_signal": "khabar"
      },
      "action": {
        "class": "ACT_VOLITIONAL",
        "textual_eval": "EVAL_NEUTRAL"
      },
      "axes": {
        "situational": "external",
        "systemic": "SYS_SOCIAL"
      },
      "evidence": {
        "support_type": "inferred"
      },
      "annotator": "expert_scholar",
      "annotated_at": "2025-12-21T09:43:14.816443"
    },
    {
      "span_id": "QBM_10236",
      "reference": {
        "surah": 35,
        "ayah": 36,
        "surah_name": "فاطر"
      },
      "text_ar": "وَٱلَّذِينَ كَفَرُوا۟ لَهُمْ نَارُ جَهَنَّمَ لَا يُقْضَىٰ عَلَيْهِمْ فَيَمُوتُوا۟ وَلَا يُخَفَّفُ عَنْهُم مِّنْ عَذَابِهَا ۚ كَذَٰلِكَ نَجْزِى كُلَّ كَفُورٍ",
      "behavior_form": "inner_state",
      "agent": {
        "type": "AGT_DISBELIEVER",
        "explicit": false
      },
      "normative": {
        "speech_mode": "informative",
        "evaluation": "blame",
        "deontic_signal": "tarhib"
      },
      "action": {
        "class": "ACT_PSYCHOLOGICAL",
        "textual_eval": "EVAL_SAYYI"
      },
      "axes": {
        "situational": "internal",
        "systemic": "SYS_SOCIAL"
      },
      "evidence": {
        "support_type": "inferred"
      },
      "annotator": "expert_scholar",
      "annotated_at": "2025-12-21T09:43:14.817443"
    },
    {
      "span_id": "QBM_10237",
      "reference": {
        "surah": 35,
        "ayah": 37,
        "surah_name": "فاطر"
      },
      "text_ar": "وَهُمْ يَصْطَرِخُونَ فِيهَا رَبَّنَآ أَخْرِجْنَا نَعْمَلْ صَـٰلِحًا غَيْرَ ٱلَّذِى كُنَّا نَعْمَلُ ۚ أَوَلَمْ نُعَمِّرْكُم مَّا يَتَذَكَّرُ فِيهِ مَن تَذَكَّرَ وَجَآءَكُمُ ٱلنَّذِيرُ ۖ فَذُوقُوا۟ فَمَا لِلظَّـٰلِمِينَ مِن نَّصِيرٍ",
      "behavior_form": "speech_act",
      "agent": {
        "type": "AGT_ALLAH",
        "explicit": true
      },
      "normative": {
        "speech_mode": "informative",
        "evaluation": "neutral",
        "deontic_signal": "khabar"
      },
      "action": {
        "class": "ACT_VOLITIONAL",
        "textual_eval": "EVAL_NEUTRAL"
      },
      "axes": {
        "situational": "external",
        "systemic": "SYS_GOD"
      },
      "evidence": {
        "support_type": "direct"
      },
      "annotator": "expert_scholar",
      "annotated_at": "2025-12-21T09:43:14.817443"
    },
    {
      "span_id": "QBM_10238",
      "reference": {
        "surah": 35,
        "ayah": 38,
        "surah_name": "فاطر"
      },
      "text_ar": "إِنَّ ٱللَّهَ عَـٰلِمُ غَيْبِ ٱلسَّمَـٰوَٰتِ وَٱلْأَرْضِ ۚ إِنَّهُۥ عَلِيمٌۢ بِذَاتِ ٱلصُّدُورِ",
      "behavior_form": "inner_state",
      "agent": {
        "type": "AGT_ALLAH",
        "explicit": true
      },
      "normative": {
        "speech_mode": "informative",
        "evaluation": "neutral",
        "deontic_signal": "khabar"
      },
      "action": {
        "class": "ACT_PSYCHOLOGICAL",
        "textual_eval": "EVAL_NEUTRAL"
      },
      "axes": {
        "situational": "internal",
        "systemic": "SYS_GOD"
      },
      "evidence": {
        "support_type": "inferred"
      },
      "annotator": "expert_scholar",
      "annotated_at": "2025-12-21T09:43:14.817443"
    },
    {
      "span_id": "QBM_10239",
      "reference": {
        "surah": 35,
        "ayah": 39,
        "surah_name": "فاطر"
      },
      "text_ar": "هُوَ ٱلَّذِى جَعَلَكُمْ خَلَـٰٓئِفَ فِى ٱلْأَرْضِ ۚ فَمَن كَفَرَ فَعَلَيْهِ كُفْرُهُۥ ۖ وَلَا يَزِيدُ ٱلْكَـٰفِرِينَ كُفْرُهُمْ عِندَ رَبِّهِمْ إِلَّا مَقْتًا ۖ وَلَا يَزِيدُ ٱلْكَـٰفِرِينَ كُفْرُهُمْ إِلَّا خَسَارًا",
      "behavior_form": "inner_state",
      "agent": {
        "type": "AGT_ALLAH",
        "explicit": true
      },
      "normative": {
        "speech_mode": "informative",
        "evaluation": "neutral",
        "deontic_signal": "khabar"
      },
      "action": {
        "class": "ACT_PSYCHOLOGICAL",
        "textual_eval": "EVAL_NEUTRAL"
      },
      "axes": {
        "situational": "internal",
        "systemic": "SYS_GOD"
      },
      "evidence": {
        "support_type": "direct"
      },
      "annotator": "expert_scholar",
      "annotated_at": "2025-12-21T09:43:14.817443"
    },
    {
      "span_id": "QBM_10240",
      "reference": {
        "surah": 35,
        "ayah": 40,
        "surah_name": "فاطر"
      },
      "text_ar": "قُلْ أَرَءَيْتُمْ شُرَكَآءَكُمُ ٱلَّذِينَ تَدْعُونَ مِن دُونِ ٱللَّهِ أَرُونِى مَاذَا خَلَقُوا۟ مِنَ ٱلْأَرْضِ أَمْ لَهُمْ شِرْكٌ فِى ٱلسَّمَـٰوَٰتِ أَمْ ءَاتَيْنَـٰهُمْ كِتَـٰبًا فَهُمْ عَلَىٰ بَيِّنَتٍ مِّنْهُ ۚ بَلْ إِن يَعِدُ ٱلظَّـٰلِمُونَ بَعْضُهُم بَعْضًا إِلَّا غُرُورًا",
      "behavior_form": "inner_state",
      "agent": {
        "type": "AGT_ALLAH",
        "explicit": true
      },
      "normative": {
        "speech_mode": "informative",
        "evaluation": "blame",
        "deontic_signal": "tarhib"
      },
      "action": {
        "class": "ACT_PSYCHOLOGICAL",
        "textual_eval": "EVAL_SAYYI"
      },
      "axes": {
        "situational": "internal",
        "systemic": "SYS_GOD"
      },
      "evidence": {
        "support_type": "inferred"
      },
      "annotator": "expert_scholar",
      "annotated_at": "2025-12-21T09:43:14.817443"
    },
    {
      "span_id": "QBM_10241",
      "reference": {
        "surah": 35,
        "ayah": 41,
        "surah_name": "فاطر"
      },
      "text_ar": "إِنَّ ٱللَّهَ يُمْسِكُ ٱلسَّمَـٰوَٰتِ وَٱلْأَرْضَ أَن تَزُولَا ۚ وَلَئِن زَالَتَآ إِنْ أَمْسَكَهُمَا مِنْ أَحَدٍ مِّنۢ بَعْدِهِۦٓ ۚ إِنَّهُۥ كَانَ حَلِيمًا غَفُورًا",
      "behavior_form": "inner_state",
      "agent": {
        "type": "AGT_ALLAH",
        "explicit": true
      },
      "normative": {
        "speech_mode": "informative",
        "evaluation": "neutral",
        "deontic_signal": "khabar"
      },
      "action": {
        "class": "ACT_PSYCHOLOGICAL",
        "textual_eval": "EVAL_NEUTRAL"
      },
      "axes": {
        "situational": "internal",
        "systemic": "SYS_GOD"
      },
      "evidence": {
        "support_type": "inferred"
      },
      "annotator": "expert_scholar",
      "annotated_at": "2025-12-21T09:43:14.817443"
    },
    {
      "span_id": "QBM_10242",
      "reference": {
        "surah": 35,
        "ayah": 42,
        "surah_name": "فاطر"
      },
      "text_ar": "وَأَقْسَمُوا۟ بِٱللَّهِ جَهْدَ أَيْمَـٰنِهِمْ لَئِن جَآءَهُمْ نَذِيرٌ لَّيَكُونُنَّ أَهْدَىٰ مِنْ إِحْدَى ٱلْأُمَمِ ۖ فَلَمَّا جَآءَهُمْ نَذِيرٌ مَّا زَادَهُمْ إِلَّا نُفُورًا",
      "behavior_form": "inner_state",
      "agent": {
        "type": "AGT_ALLAH",
        "explicit": true
      },
      "normative": {
        "speech_mode": "informative",
        "evaluation": "neutral",
        "deontic_signal": "khabar"
      },
      "action": {
        "class": "ACT_PSYCHOLOGICAL",
        "textual_eval": "EVAL_NEUTRAL"
      },
      "axes": {
        "situational": "internal",
        "systemic": "SYS_GOD"
      },
      "evidence": {
        "support_type": "inferred"
      },
      "annotator": "expert_scholar",
      "annotated_at": "2025-12-21T09:43:14.818443"
    },
    {
      "span_id": "QBM_10243",
      "reference": {
        "surah": 35,
        "ayah": 43,
        "surah_name": "فاطر"
      },
      "text_ar": "ٱسْتِكْبَارًا فِى ٱلْأَرْضِ وَمَكْرَ ٱلسَّيِّئِ ۚ وَلَا يَحِيقُ ٱلْمَكْرُ ٱلسَّيِّئُ إِلَّا بِأَهْلِهِۦ ۚ فَهَلْ يَنظُرُونَ إِلَّا سُنَّتَ ٱلْأَوَّلِينَ ۚ فَلَن تَجِدَ لِسُنَّتِ ٱللَّهِ تَبْدِيلًا ۖ وَلَن تَجِدَ لِسُنَّتِ ٱللَّهِ تَحْوِيلًا",
      "behavior_form": "inner_state",
      "agent": {
        "type": "AGT_ALLAH",
        "explicit": true
      },
      "normative": {
        "speech_mode": "interrogative",
        "evaluation": "neutral",
        "deontic_signal": "khabar"
      },
      "action": {
        "class": "ACT_PSYCHOLOGICAL",
        "textual_eval": "EVAL_NEUTRAL"
      },
      "axes": {
        "situational": "internal",
        "systemic": "SYS_GOD"
      },
      "evidence": {
        "support_type": "inferred"
      },
      "annotator": "expert_scholar",
      "annotated_at": "2025-12-21T09:43:14.818443"
    },
    {
      "span_id": "QBM_10244",
      "reference": {
        "surah": 35,
        "ayah": 44,
        "surah_name": "فاطر"
      },
      "text_ar": "أَوَلَمْ يَسِيرُوا۟ فِى ٱلْأَرْضِ فَيَنظُرُوا۟ كَيْفَ كَانَ عَـٰقِبَةُ ٱلَّذِينَ مِن قَبْلِهِمْ وَكَانُوٓا۟ أَشَدَّ مِنْهُمْ قُوَّةً ۚ وَمَا كَانَ ٱللَّهُ لِيُعْجِزَهُۥ مِن شَىْءٍ فِى ٱلسَّمَـٰوَٰتِ وَلَا فِى ٱلْأَرْضِ ۚ إِنَّهُۥ كَانَ عَلِيمًا قَدِيرًا",
      "behavior_form": "inner_state",
      "agent": {
        "type": "AGT_ALLAH",
        "explicit": true
      },
      "normative": {
        "speech_mode": "informative",
        "evaluation": "neutral",
        "deontic_signal": "khabar"
      },
      "action": {
        "class": "ACT_PSYCHOLOGICAL",
        "textual_eval": "EVAL_NEUTRAL"
      },
      "axes": {
        "situational": "internal",
        "systemic": "SYS_GOD"
      },
      "evidence": {
        "support_type": "inferred"
      },
      "annotator": "expert_scholar",
      "annotated_at": "2025-12-21T09:43:14.818443"
    },
    {
      "span_id": "QBM_10245",
      "reference": {
        "surah": 35,
        "ayah": 45,
        "surah_name": "فاطر"
      },
      "text_ar": "وَلَوْ يُؤَاخِذُ ٱللَّهُ ٱلنَّاسَ بِمَا كَسَبُوا۟ مَا تَرَكَ عَلَىٰ ظَهْرِهَا مِن دَآبَّةٍ وَلَـٰكِن يُؤَخِّرُهُمْ إِلَىٰٓ أَجَلٍ مُّسَمًّى ۖ فَإِذَا جَآءَ أَجَلُهُمْ فَإِنَّ ٱللَّهَ كَانَ بِعِبَادِهِۦ بَصِيرًۢا",
      "behavior_form": "inner_state",
      "agent": {
        "type": "AGT_ALLAH",
        "explicit": true
      },
      "normative": {
        "speech_mode": "informative",
        "evaluation": "neutral",
        "deontic_signal": "khabar"
      },
      "action": {
        "class": "ACT_PSYCHOLOGICAL",
        "textual_eval": "EVAL_NEUTRAL"
      },
      "axes": {
        "situational": "internal",
        "systemic": "SYS_GOD"
      },
      "evidence": {
        "support_type": "inferred"
      },
      "annotator": "expert_scholar",
      "annotated_at": "2025-12-21T09:43:14.818443"
    },
    {
      "span_id": "QBM_10501",
      "reference": {
        "surah": 36,
        "ayah": 1,
        "surah_name": "يس"
      },
      "text_ar": "يسٓ",
      "behavior_form": "inner_state",
      "agent": {
        "type": "AGT_DISBELIEVER",
        "explicit": false
      },
      "normative": {
        "speech_mode": "informative",
        "evaluation": "neutral",
        "deontic_signal": "khabar"
      },
      "action": {
        "class": "ACT_PSYCHOLOGICAL",
        "textual_eval": "EVAL_NEUTRAL"
      },
      "axes": {
        "situational": "internal",
        "systemic": "SYS_SOCIAL"
      },
      "evidence": {
        "support_type": "inferred"
      },
      "annotator": "expert_scholar",
      "annotated_at": "2025-12-21T09:43:14.818443"
    },
    {
      "span_id": "QBM_10502",
      "reference": {
        "surah": 36,
        "ayah": 2,
        "surah_name": "يس"
      },
      "text_ar": "وَٱلْقُرْءَانِ ٱلْحَكِيمِ",
      "behavior_form": "inner_state",
      "agent": {
        "type": "AGT_ALLAH",
        "explicit": true
      },
      "normative": {
        "speech_mode": "informative",
        "evaluation": "neutral",
        "deontic_signal": "khabar"
      },
      "action": {
        "class": "ACT_PSYCHOLOGICAL",
        "textual_eval": "EVAL_NEUTRAL"
      },
      "axes": {
        "situational": "internal",
        "systemic": "SYS_SOCIAL"
      },
      "evidence": {
        "support_type": "inferred"
      },
      "annotator": "expert_scholar",
      "annotated_at": "2025-12-21T09:43:14.818443"
    },
    {
      "span_id": "QBM_10503",
      "reference": {
        "surah": 36,
        "ayah": 3,
        "surah_name": "يس"
      },
      "text_ar": "إِنَّكَ لَمِنَ ٱلْمُرْسَلِينَ",
      "behavior_form": "inner_state",
      "agent": {
        "type": "AGT_DISBELIEVER",
        "explicit": false
      },
      "normative": {
        "speech_mode": "interrogative",
        "evaluation": "neutral",
        "deontic_signal": "khabar"
      },
      "action": {
        "class": "ACT_PSYCHOLOGICAL",
        "textual_eval": "EVAL_NEUTRAL"
      },
      "axes": {
        "situational": "internal",
        "systemic": "SYS_SOCIAL"
      },
      "evidence": {
        "support_type": "inferred"
      },
      "annotator": "expert_scholar",
      "annotated_at": "2025-12-21T09:43:14.818443"
    },
    {
      "span_id": "QBM_10504",
      "reference": {
        "surah": 36,
        "ayah": 4,
        "surah_name": "يس"
      },
      "text_ar": "عَلَىٰ صِرَٰطٍ مُّسْتَقِيمٍ",
      "behavior_form": "inner_state",
      "agent": {
        "type": "AGT_BELIEVER",
        "explicit": false
      },
      "normative": {
        "speech_mode": "informative",
        "evaluation": "neutral",
        "deontic_signal": "khabar"
      },
      "action": {
        "class": "ACT_PSYCHOLOGICAL",
        "textual_eval": "EVAL_NEUTRAL"
      },
      "axes": {
        "situational": "internal",
        "systemic": "SYS_SOCIAL"
      },
      "evidence": {
        "support_type": "inferred"
      },
      "annotator": "expert_scholar",
      "annotated_at": "2025-12-21T09:43:14.818443"
    },
    {
      "span_id": "QBM_10505",
      "reference": {
        "surah": 36,
        "ayah": 5,
        "surah_name": "يس"
      },
      "text_ar": "تَنزِيلَ ٱلْعَزِيزِ ٱلرَّحِيمِ",
      "behavior_form": "inner_state",
      "agent": {
        "type": "AGT_ALLAH",
        "explicit": true
      },
      "normative": {
        "speech_mode": "informative",
        "evaluation": "neutral",
        "deontic_signal": "khabar"
      },
      "action": {
        "class": "ACT_PSYCHOLOGICAL",
        "textual_eval": "EVAL_NEUTRAL"
      },
      "axes": {
        "situational": "internal",
        "systemic": "SYS_SOCIAL"
      },
      "evidence": {
        "support_type": "inferred"
      },
      "annotator": "expert_scholar",
      "annotated_at": "2025-12-21T09:43:14.818443"
    },
    {
      "span_id": "QBM_10506",
      "reference": {
        "surah": 36,
        "ayah": 6,
        "surah_name": "يس"
      },
      "text_ar": "لِتُنذِرَ قَوْمًا مَّآ أُنذِرَ ءَابَآؤُهُمْ فَهُمْ غَـٰفِلُونَ",
      "behavior_form": "inner_state",
      "agent": {
        "type": "AGT_BELIEVER",
        "explicit": false
      },
      "normative": {
        "speech_mode": "informative",
        "evaluation": "neutral",
        "deontic_signal": "khabar"
      },
      "action": {
        "class": "ACT_PSYCHOLOGICAL",
        "textual_eval": "EVAL_NEUTRAL"
      },
      "axes": {
        "situational": "internal",
        "systemic": "SYS_SOCIAL"
      },
      "evidence": {
        "support_type": "inferred"
      },
      "annotator": "expert_scholar",
      "annotated_at": "2025-12-21T09:43:14.819496"
    },
    {
      "span_id": "QBM_10507",
      "reference": {
        "surah": 36,
        "ayah": 7,
        "surah_name": "يس"
      },
      "text_ar": "لَقَدْ حَقَّ ٱلْقَوْلُ عَلَىٰٓ أَكْثَرِهِمْ فَهُمْ لَا يُؤْمِنُونَ",
      "behavior_form": "inner_state",
      "agent": {
        "type": "AGT_HUMAN_GENERAL",
        "explicit": false
      },
      "normative": {
        "speech_mode": "informative",
        "evaluation": "neutral",
        "deontic_signal": "khabar"
      },
      "action": {
        "class": "ACT_PSYCHOLOGICAL",
        "textual_eval": "EVAL_NEUTRAL"
      },
      "axes": {
        "situational": "internal",
        "systemic": "SYS_SOCIAL"
      },
      "evidence": {
        "support_type": "inferred"
      },
      "annotator": "expert_scholar",
      "annotated_at": "2025-12-21T09:43:14.819540"
    },
    {
      "span_id": "QBM_10508",
      "reference": {
        "surah": 36,
        "ayah": 8,
        "surah_name": "يس"
      },
      "text_ar": "إِنَّا جَعَلْنَا فِىٓ أَعْنَـٰقِهِمْ أَغْلَـٰلًا فَهِىَ إِلَى ٱلْأَذْقَانِ فَهُم مُّقْمَحُونَ",
      "behavior_form": "inner_state",
      "agent": {
        "type": "AGT_BELIEVER",
        "explicit": false
      },
      "normative": {
        "speech_mode": "informative",
        "evaluation": "neutral",
        "deontic_signal": "khabar"
      },
      "action": {
        "class": "ACT_PSYCHOLOGICAL",
        "textual_eval": "EVAL_NEUTRAL"
      },
      "axes": {
        "situational": "internal",
        "systemic": "SYS_SOCIAL"
      },
      "evidence": {
        "support_type": "inferred"
      },
      "annotator": "expert_scholar",
      "annotated_at": "2025-12-21T09:43:14.819540"
    },
    {
      "span_id": "QBM_10509",
      "reference": {
        "surah": 36,
        "ayah": 9,
        "surah_name": "يس"
      },
      "text_ar": "وَجَعَلْنَا مِنۢ بَيْنِ أَيْدِيهِمْ سَدًّا وَمِنْ خَلْفِهِمْ سَدًّا فَأَغْشَيْنَـٰهُمْ فَهُمْ لَا يُبْصِرُونَ",
      "behavior_form": "inner_state",
      "agent": {
        "type": "AGT_BELIEVER",
        "explicit": false
      },
      "normative": {
        "speech_mode": "informative",
        "evaluation": "neutral",
        "deontic_signal": "khabar"
      },
      "action": {
        "class": "ACT_PSYCHOLOGICAL",
        "textual_eval": "EVAL_NEUTRAL"
      },
      "axes": {
        "situational": "internal",
        "systemic": "SYS_SOCIAL"
      },
      "evidence": {
        "support_type": "inferred"
      },
      "annotator": "expert_scholar",
      "annotated_at": "2025-12-21T09:43:14.819540"
    },
    {
      "span_id": "QBM_10510",
      "reference": {
        "surah": 36,
        "ayah": 10,
        "surah_name": "يس"
      },
      "text_ar": "وَسَوَآءٌ عَلَيْهِمْ ءَأَنذَرْتَهُمْ أَمْ لَمْ تُنذِرْهُمْ لَا يُؤْمِنُونَ",
      "behavior_form": "inner_state",
      "agent": {
        "type": "AGT_HUMAN_GENERAL",
        "explicit": false
      },
      "normative": {
        "speech_mode": "informative",
        "evaluation": "neutral",
        "deontic_signal": "khabar"
      },
      "action": {
        "class": "ACT_PSYCHOLOGICAL",
        "textual_eval": "EVAL_NEUTRAL"
      },
      "axes": {
        "situational": "internal",
        "systemic": "SYS_SOCIAL"
      },
      "evidence": {
        "support_type": "inferred"
      },
      "annotator": "expert_scholar",
      "annotated_at": "2025-12-21T09:43:14.819540"
    },
    {
      "span_id": "QBM_10511",
      "reference": {
        "surah": 36,
        "ayah": 11,
        "surah_name": "يس"
      },
      "text_ar": "إِنَّمَا تُنذِرُ مَنِ ٱتَّبَعَ ٱلذِّكْرَ وَخَشِىَ ٱلرَّحْمَـٰنَ بِٱلْغَيْبِ ۖ فَبَشِّرْهُ بِمَغْفِرَةٍ وَأَجْرٍ كَرِيمٍ",
      "behavior_form": "inner_state",
      "agent": {
        "type": "AGT_DISBELIEVER",
        "explicit": false
      },
      "normative": {
        "speech_mode": "interrogative",
        "evaluation": "blame",
        "deontic_signal": "khabar"
      },
      "action": {
        "class": "ACT_PSYCHOLOGICAL",
        "textual_eval": "EVAL_SAYYI"
      },
      "axes": {
        "situational": "internal",
        "systemic": "SYS_SOCIAL"
      },
      "evidence": {
        "support_type": "inferred"
      },
      "annotator": "expert_scholar",
      "annotated_at": "2025-12-21T09:43:14.819540"
    },
    {
      "span_id": "QBM_10512",
      "reference": {
        "surah": 36,
        "ayah": 12,
        "surah_name": "يس"
      },
      "text_ar": "إِنَّا نَحْنُ نُحْىِ ٱلْمَوْتَىٰ وَنَكْتُبُ مَا قَدَّمُوا۟ وَءَاثَـٰرَهُمْ ۚ وَكُلَّ شَىْءٍ أَحْصَيْنَـٰهُ فِىٓ إِمَامٍ مُّبِينٍ",
      "behavior_form": "inner_state",
      "agent": {
        "type": "AGT_ALLAH",
        "explicit": true
      },
      "normative": {
        "speech_mode": "informative",
        "evaluation": "neutral",
        "deontic_signal": "khabar"
      },
      "action": {
        "class": "ACT_PSYCHOLOGICAL",
        "textual_eval": "EVAL_NEUTRAL"
      },
      "axes": {
        "situational": "internal",
        "systemic": "SYS_SOCIAL"
      },
      "evidence": {
        "support_type": "inferred"
      },
      "annotator": "expert_scholar",
      "annotated_at": "2025-12-21T09:43:14.819540"
    },
    {
      "span_id": "QBM_10513",
      "reference": {
        "surah": 36,
        "ayah": 13,
        "surah_name": "يس"
      },
      "text_ar": "وَٱضْرِبْ لَهُم مَّثَلًا أَصْحَـٰبَ ٱلْقَرْيَةِ إِذْ جَآءَهَا ٱلْمُرْسَلُونَ",
      "behavior_form": "physical_act",
      "agent": {
        "type": "AGT_ALLAH",
        "explicit": true
      },
      "normative": {
        "speech_mode": "informative",
        "evaluation": "neutral",
        "deontic_signal": "khabar"
      },
      "action": {
        "class": "ACT_VOLITIONAL",
        "textual_eval": "EVAL_NEUTRAL"
      },
      "axes": {
        "situational": "external",
        "systemic": "SYS_GOD"
      },
      "evidence": {
        "support_type": "inferred"
      },
      "annotator": "expert_scholar",
      "annotated_at": "2025-12-21T09:43:14.819540"
    },
    {
      "span_id": "QBM_10514",
      "reference": {
        "surah": 36,
        "ayah": 14,
        "surah_name": "يس"
      },
      "text_ar": "إِذْ أَرْسَلْنَآ إِلَيْهِمُ ٱثْنَيْنِ فَكَذَّبُوهُمَا فَعَزَّزْنَا بِثَالِثٍ فَقَالُوٓا۟ إِنَّآ إِلَيْكُم مُّرْسَلُونَ",
      "behavior_form": "speech_act",
      "agent": {
        "type": "AGT_DISBELIEVER",
        "explicit": false
      },
      "normative": {
        "speech_mode": "informative",
        "evaluation": "neutral",
        "deontic_signal": "khabar"
      },
      "action": {
        "class": "ACT_VOLITIONAL",
        "textual_eval": "EVAL_NEUTRAL"
      },
      "axes": {
        "situational": "external",
        "systemic": "SYS_SOCIAL"
      },
      "evidence": {
        "support_type": "direct"
      },
      "annotator": "expert_scholar",
      "annotated_at": "2025-12-21T09:43:14.819540"
    },
    {
      "span_id": "QBM_10515",
      "reference": {
        "surah": 36,
        "ayah": 15,
        "surah_name": "يس"
      },
      "text_ar": "قَالُوا۟ مَآ أَنتُمْ إِلَّا بَشَرٌ مِّثْلُنَا وَمَآ أَنزَلَ ٱلرَّحْمَـٰنُ مِن شَىْءٍ إِنْ أَنتُمْ إِلَّا تَكْذِبُونَ",
      "behavior_form": "speech_act",
      "agent": {
        "type": "AGT_HUMAN_GENERAL",
        "explicit": false
      },
      "normative": {
        "speech_mode": "interrogative",
        "evaluation": "blame",
        "deontic_signal": "khabar"
      },
      "action": {
        "class": "ACT_VOLITIONAL",
        "textual_eval": "EVAL_SAYYI"
      },
      "axes": {
        "situational": "external",
        "systemic": "SYS_SOCIAL"
      },
      "evidence": {
        "support_type": "direct"
      },
      "annotator": "expert_scholar",
      "annotated_at": "2025-12-21T09:43:14.819540"
    },
    {
      "span_id": "QBM_10516",
      "reference": {
        "surah": 36,
        "ayah": 16,
        "surah_name": "يس"
      },
      "text_ar": "قَالُوا۟ رَبُّنَا يَعْلَمُ إِنَّآ إِلَيْكُمْ لَمُرْسَلُونَ",
      "behavior_form": "inner_state",
      "agent": {
        "type": "AGT_ALLAH",
        "explicit": true
      },
      "normative": {
        "speech_mode": "informative",
        "evaluation": "neutral",
        "deontic_signal": "khabar"
      },
      "action": {
        "class": "ACT_PSYCHOLOGICAL",
        "textual_eval": "EVAL_NEUTRAL"
      },
      "axes": {
        "situational": "internal",
        "systemic": "SYS_GOD"
      },
      "evidence": {
        "support_type": "direct"
      },
      "annotator": "expert_scholar",
      "annotated_at": "2025-12-21T09:43:14.820539"
    },
    {
      "span_id": "QBM_10517",
      "reference": {
        "surah": 36,
        "ayah": 17,
        "surah_name": "يس"
      },
      "text_ar": "وَمَا عَلَيْنَآ إِلَّا ٱلْبَلَـٰغُ ٱلْمُبِينُ",
      "behavior_form": "inner_state",
      "agent": {
        "type": "AGT_HUMAN_GENERAL",
        "explicit": false
      },
      "normative": {
        "speech_mode": "interrogative",
        "evaluation": "neutral",
        "deontic_signal": "khabar"
      },
      "action": {
        "class": "ACT_PSYCHOLOGICAL",
        "textual_eval": "EVAL_NEUTRAL"
      },
      "axes": {
        "situational": "internal",
        "systemic": "SYS_SOCIAL"
      },
      "evidence": {
        "support_type": "inferred"
      },
      "annotator": "expert_scholar",
      "annotated_at": "2025-12-21T09:43:14.820539"
    },
    {
      "span_id": "QBM_10518",
      "reference": {
        "surah": 36,
        "ayah": 18,
        "surah_name": "يس"
      },
      "text_ar": "قَالُوٓا۟ إِنَّا تَطَيَّرْنَا بِكُمْ ۖ لَئِن لَّمْ تَنتَهُوا۟ لَنَرْجُمَنَّكُمْ وَلَيَمَسَّنَّكُم مِّنَّا عَذَابٌ أَلِيمٌ",
      "behavior_form": "speech_act",
      "agent": {
        "type": "AGT_DISBELIEVER",
        "explicit": false
      },
      "normative": {
        "speech_mode": "informative",
        "evaluation": "blame",
        "deontic_signal": "tarhib"
      },
      "action": {
        "class": "ACT_VOLITIONAL",
        "textual_eval": "EVAL_SAYYI"
      },
      "axes": {
        "situational": "external",
        "systemic": "SYS_SOCIAL"
      },
      "evidence": {
        "support_type": "direct"
      },
      "annotator": "expert_scholar",
      "annotated_at": "2025-12-21T09:43:14.820539"
    },
    {
      "span_id": "QBM_10519",
      "reference": {
        "surah": 36,
        "ayah": 19,
        "surah_name": "يس"
      },
      "text_ar": "قَالُوا۟ طَـٰٓئِرُكُم مَّعَكُمْ ۚ أَئِن ذُكِّرْتُم ۚ بَلْ أَنتُمْ قَوْمٌ مُّسْرِفُونَ",
      "behavior_form": "speech_act",
      "agent": {
        "type": "AGT_HUMAN_GENERAL",
        "explicit": false
      },
      "normative": {
        "speech_mode": "informative",
        "evaluation": "neutral",
        "deontic_signal": "khabar"
      },
      "action": {
        "class": "ACT_VOLITIONAL",
        "textual_eval": "EVAL_NEUTRAL"
      },
      "axes": {
        "situational": "external",
        "systemic": "SYS_SOCIAL"
      },
      "evidence": {
        "support_type": "direct"
      },
      "annotator": "expert_scholar",
      "annotated_at": "2025-12-21T09:43:14.820539"
    },
    {
      "span_id": "QBM_10520",
      "reference": {
        "surah": 36,
        "ayah": 20,
        "surah_name": "يس"
      },
      "text_ar": "وَجَآءَ مِنْ أَقْصَا ٱلْمَدِينَةِ رَجُلٌ يَسْعَىٰ قَالَ يَـٰقَوْمِ ٱتَّبِعُوا۟ ٱلْمُرْسَلِينَ",
      "behavior_form": "speech_act",
      "agent": {
        "type": "AGT_BELIEVER",
        "explicit": false
      },
      "normative": {
        "speech_mode": "interrogative",
        "evaluation": "neutral",
        "deontic_signal": "khabar"
      },
      "action": {
        "class": "ACT_VOLITIONAL",
        "textual_eval": "EVAL_NEUTRAL"
      },
      "axes": {
        "situational": "external",
        "systemic": "SYS_SOCIAL"
      },
      "evidence": {
        "support_type": "direct"
      },
      "annotator": "expert_scholar",
      "annotated_at": "2025-12-21T09:43:14.820539"
    },
    {
      "span_id": "QBM_10521",
      "reference": {
        "surah": 36,
        "ayah": 21,
        "surah_name": "يس"
      },
      "text_ar": "ٱتَّبِعُوا۟ مَن لَّا يَسْـَٔلُكُمْ أَجْرًا وَهُم مُّهْتَدُونَ",
      "behavior_form": "relational_act",
      "agent": {
        "type": "AGT_BELIEVER",
        "explicit": false
      },
      "normative": {
        "speech_mode": "informative",
        "evaluation": "neutral",
        "deontic_signal": "khabar"
      },
      "action": {
        "class": "ACT_VOLITIONAL",
        "textual_eval": "EVAL_NEUTRAL"
      },
      "axes": {
        "situational": "internal",
        "systemic": "SYS_SOCIAL"
      },
      "evidence": {
        "support_type": "inferred"
      },
      "annotator": "expert_scholar",
      "annotated_at": "2025-12-21T09:43:14.820539"
    },
    {
      "span_id": "QBM_10522",
      "reference": {
        "surah": 36,
        "ayah": 22,
        "surah_name": "يس"
      },
      "text_ar": "وَمَا لِىَ لَآ أَعْبُدُ ٱلَّذِى فَطَرَنِى وَإِلَيْهِ تُرْجَعُونَ",
      "behavior_form": "inner_state",
      "agent": {
        "type": "AGT_DISBELIEVER",
        "explicit": false
      },
      "normative": {
        "speech_mode": "interrogative",
        "evaluation": "neutral",
        "deontic_signal": "khabar"
      },
      "action": {
        "class": "ACT_PSYCHOLOGICAL",
        "textual_eval": "EVAL_NEUTRAL"
      },
      "axes": {
        "situational": "internal",
        "systemic": "SYS_SOCIAL"
      },
      "evidence": {
        "support_type": "inferred"
      },
      "annotator": "expert_scholar",
      "annotated_at": "2025-12-21T09:43:14.820539"
    },
    {
      "span_id": "QBM_10523",
      "reference": {
        "surah": 36,
        "ayah": 23,
        "surah_name": "يس"
      },
      "text_ar": "ءَأَتَّخِذُ مِن دُونِهِۦٓ ءَالِهَةً إِن يُرِدْنِ ٱلرَّحْمَـٰنُ بِضُرٍّ لَّا تُغْنِ عَنِّى شَفَـٰعَتُهُمْ شَيْـًٔا وَلَا يُنقِذُونِ",
      "behavior_form": "relational_act",
      "agent": {
        "type": "AGT_BELIEVER",
        "explicit": false
      },
      "normative": {
        "speech_mode": "informative",
        "evaluation": "neutral",
        "deontic_signal": "khabar"
      },
      "action": {
        "class": "ACT_VOLITIONAL",
        "textual_eval": "EVAL_NEUTRAL"
      },
      "axes": {
        "situational": "internal",
        "systemic": "SYS_SOCIAL"
      },
      "evidence": {
        "support_type": "inferred"
      },
      "annotator": "expert_scholar",
      "annotated_at": "2025-12-21T09:43:14.820539"
    },
    {
      "span_id": "QBM_10524",
      "reference": {
        "surah": 36,
        "ayah": 24,
        "surah_name": "يس"
      },
      "text_ar": "إِنِّىٓ إِذًا لَّفِى ضَلَـٰلٍ مُّبِينٍ",
      "behavior_form": "inner_state",
      "agent": {
        "type": "AGT_HUMAN_GENERAL",
        "explicit": false
      },
      "normative": {
        "speech_mode": "informative",
        "evaluation": "neutral",
        "deontic_signal": "khabar"
      },
      "action": {
        "class": "ACT_PSYCHOLOGICAL",
        "textual_eval": "EVAL_NEUTRAL"
      },
      "axes": {
        "situational": "internal",
        "systemic": "SYS_SOCIAL"
      },
      "evidence": {
        "support_type": "inferred"
      },
      "annotator": "expert_scholar",
      "annotated_at": "2025-12-21T09:43:14.820539"
    },
    {
      "span_id": "QBM_10525",
      "reference": {
        "surah": 36,
        "ayah": 25,
        "surah_name": "يس"
      },
      "text_ar": "إِنِّىٓ ءَامَنتُ بِرَبِّكُمْ فَٱسْمَعُونِ",
      "behavior_form": "relational_act",
      "agent": {
        "type": "AGT_ALLAH",
        "explicit": true
      },
      "normative": {
        "speech_mode": "interrogative",
        "evaluation": "neutral",
        "deontic_signal": "khabar"
      },
      "action": {
        "class": "ACT_VOLITIONAL",
        "textual_eval": "EVAL_NEUTRAL"
      },
      "axes": {
        "situational": "internal",
        "systemic": "SYS_GOD"
      },
      "evidence": {
        "support_type": "inferred"
      },
      "annotator": "expert_scholar",
      "annotated_at": "2025-12-21T09:43:14.820539"
    },
    {
      "span_id": "QBM_10526",
      "reference": {
        "surah": 36,
        "ayah": 26,
        "surah_name": "يس"
      },
      "text_ar": "قِيلَ ٱدْخُلِ ٱلْجَنَّةَ ۖ قَالَ يَـٰلَيْتَ قَوْمِى يَعْلَمُونَ",
      "behavior_form": "inner_state",
      "agent": {
        "type": "AGT_HUMAN_GENERAL",
        "explicit": false
      },
      "normative": {
        "speech_mode": "informative",
        "evaluation": "neutral",
        "deontic_signal": "khabar"
      },
      "action": {
        "class": "ACT_PSYCHOLOGICAL",
        "textual_eval": "EVAL_NEUTRAL"
      },
      "axes": {
        "situational": "internal",
        "systemic": "SYS_SOCIAL"
      },
      "evidence": {
        "support_type": "direct"
      },
      "annotator": "expert_scholar",
      "annotated_at": "2025-12-21T09:43:14.820539"
    },
    {
      "span_id": "QBM_10527",
      "reference": {
        "surah": 36,
        "ayah": 27,
        "surah_name": "يس"
      },
      "text_ar": "بِمَا غَفَرَ لِى رَبِّى وَجَعَلَنِى مِنَ ٱلْمُكْرَمِينَ",
      "behavior_form": "inner_state",
      "agent": {
        "type": "AGT_ALLAH",
        "explicit": true
      },
      "normative": {
        "speech_mode": "interrogative",
        "evaluation": "neutral",
        "deontic_signal": "khabar"
      },
      "action": {
        "class": "ACT_PSYCHOLOGICAL",
        "textual_eval": "EVAL_NEUTRAL"
      },
      "axes": {
        "situational": "internal",
        "systemic": "SYS_GOD"
      },
      "evidence": {
        "support_type": "inferred"
      },
      "annotator": "expert_scholar",
      "annotated_at": "2025-12-21T09:43:14.821538"
    },
    {
      "span_id": "QBM_10528",
      "reference": {
        "surah": 36,
        "ayah": 28,
        "surah_name": "يس"
      },
      "text_ar": "وَمَآ أَنزَلْنَا عَلَىٰ قَوْمِهِۦ مِنۢ بَعْدِهِۦ مِن جُندٍ مِّنَ ٱلسَّمَآءِ وَمَا كُنَّا مُنزِلِينَ",
      "behavior_form": "inner_state",
      "agent": {
        "type": "AGT_HUMAN_GENERAL",
        "explicit": false
      },
      "normative": {
        "speech_mode": "interrogative",
        "evaluation": "neutral",
        "deontic_signal": "khabar"
      },
      "action": {
        "class": "ACT_PSYCHOLOGICAL",
        "textual_eval": "EVAL_NEUTRAL"
      },
      "axes": {
        "situational": "internal",
        "systemic": "SYS_SOCIAL"
      },
      "evidence": {
        "support_type": "inferred"
      },
      "annotator": "expert_scholar",
      "annotated_at": "2025-12-21T09:43:14.821538"
    },
    {
      "span_id": "QBM_10529",
      "reference": {
        "surah": 36,
        "ayah": 29,
        "surah_name": "يس"
      },
      "text_ar": "إِن كَانَتْ إِلَّا صَيْحَةً وَٰحِدَةً فَإِذَا هُمْ خَـٰمِدُونَ",
      "behavior_form": "inner_state",
      "agent": {
        "type": "AGT_DISBELIEVER",
        "explicit": false
      },
      "normative": {
        "speech_mode": "informative",
        "evaluation": "neutral",
        "deontic_signal": "khabar"
      },
      "action": {
        "class": "ACT_PSYCHOLOGICAL",
        "textual_eval": "EVAL_NEUTRAL"
      },
      "axes": {
        "situational": "internal",
        "systemic": "SYS_SOCIAL"
      },
      "evidence": {
        "support_type": "inferred"
      },
      "annotator": "expert_scholar",
      "annotated_at": "2025-12-21T09:43:14.821538"
    },
    {
      "span_id": "QBM_10530",
      "reference": {
        "surah": 36,
        "ayah": 30,
        "surah_name": "يس"
      },
      "text_ar": "يَـٰحَسْرَةً عَلَى ٱلْعِبَادِ ۚ مَا يَأْتِيهِم مِّن رَّسُولٍ إِلَّا كَانُوا۟ بِهِۦ يَسْتَهْزِءُونَ",
      "behavior_form": "inner_state",
      "agent": {
        "type": "AGT_HUMAN_GENERAL",
        "explicit": false
      },
      "normative": {
        "speech_mode": "informative",
        "evaluation": "neutral",
        "deontic_signal": "khabar"
      },
      "action": {
        "class": "ACT_PSYCHOLOGICAL",
        "textual_eval": "EVAL_NEUTRAL"
      },
      "axes": {
        "situational": "internal",
        "systemic": "SYS_SOCIAL"
      },
      "evidence": {
        "support_type": "inferred"
      },
      "annotator": "expert_scholar",
      "annotated_at": "2025-12-21T09:43:14.821538"
    },
    {
      "span_id": "QBM_10531",
      "reference": {
        "surah": 36,
        "ayah": 31,
        "surah_name": "يس"
      },
      "text_ar": "أَلَمْ يَرَوْا۟ كَمْ أَهْلَكْنَا قَبْلَهُم مِّنَ ٱلْقُرُونِ أَنَّهُمْ إِلَيْهِمْ لَا يَرْجِعُونَ",
      "behavior_form": "inner_state",
      "agent": {
        "type": "AGT_HUMAN_GENERAL",
        "explicit": false
      },
      "normative": {
        "speech_mode": "informative",
        "evaluation": "neutral",
        "deontic_signal": "khabar"
      },
      "action": {
        "class": "ACT_PSYCHOLOGICAL",
        "textual_eval": "EVAL_NEUTRAL"
      },
      "axes": {
        "situational": "internal",
        "systemic": "SYS_SOCIAL"
      },
      "evidence": {
        "support_type": "inferred"
      },
      "annotator": "expert_scholar",
      "annotated_at": "2025-12-21T09:43:14.821538"
    },
    {
      "span_id": "QBM_10532",
      "reference": {
        "surah": 36,
        "ayah": 32,
        "surah_name": "يس"
      },
      "text_ar": "وَإِن كُلٌّ لَّمَّا جَمِيعٌ لَّدَيْنَا مُحْضَرُونَ",
      "behavior_form": "inner_state",
      "agent": {
        "type": "AGT_HUMAN_GENERAL",
        "explicit": false
      },
      "normative": {
        "speech_mode": "interrogative",
        "evaluation": "neutral",
        "deontic_signal": "khabar"
      },
      "action": {
        "class": "ACT_PSYCHOLOGICAL",
        "textual_eval": "EVAL_NEUTRAL"
      },
      "axes": {
        "situational": "internal",
        "systemic": "SYS_SOCIAL"
      },
      "evidence": {
        "support_type": "inferred"
      },
      "annotator": "expert_scholar",
      "annotated_at": "2025-12-21T09:43:14.821538"
    },
    {
      "span_id": "QBM_10533",
      "reference": {
        "surah": 36,
        "ayah": 33,
        "surah_name": "يس"
      },
      "text_ar": "وَءَايَةٌ لَّهُمُ ٱلْأَرْضُ ٱلْمَيْتَةُ أَحْيَيْنَـٰهَا وَأَخْرَجْنَا مِنْهَا حَبًّا فَمِنْهُ يَأْكُلُونَ",
      "behavior_form": "inner_state",
      "agent": {
        "type": "AGT_HUMAN_GENERAL",
        "explicit": false
      },
      "normative": {
        "speech_mode": "informative",
        "evaluation": "neutral",
        "deontic_signal": "khabar"
      },
      "action": {
        "class": "ACT_PSYCHOLOGICAL",
        "textual_eval": "EVAL_NEUTRAL"
      },
      "axes": {
        "situational": "internal",
        "systemic": "SYS_SOCIAL"
      },
      "evidence": {
        "support_type": "inferred"
      },
      "annotator": "expert_scholar",
      "annotated_at": "2025-12-21T09:43:14.821538"
    },
    {
      "span_id": "QBM_10534",
      "reference": {
        "surah": 36,
        "ayah": 34,
        "surah_name": "يس"
      },
      "text_ar": "وَجَعَلْنَا فِيهَا جَنَّـٰتٍ مِّن نَّخِيلٍ وَأَعْنَـٰبٍ وَفَجَّرْنَا فِيهَا مِنَ ٱلْعُيُونِ",
      "behavior_form": "inner_state",
      "agent": {
        "type": "AGT_BELIEVER",
        "explicit": false
      },
      "normative": {
        "speech_mode": "interrogative",
        "evaluation": "neutral",
        "deontic_signal": "khabar"
      },
      "action": {
        "class": "ACT_PSYCHOLOGICAL",
        "textual_eval": "EVAL_NEUTRAL"
      },
      "axes": {
        "situational": "internal",
        "systemic": "SYS_SOCIAL"
      },
      "evidence": {
        "support_type": "inferred"
      },
      "annotator": "expert_scholar",
      "annotated_at": "2025-12-21T09:43:14.821538"
    },
    {
      "span_id": "QBM_10535",
      "reference": {
        "surah": 36,
        "ayah": 35,
        "surah_name": "يس"
      },
      "text_ar": "لِيَأْكُلُوا۟ مِن ثَمَرِهِۦ وَمَا عَمِلَتْهُ أَيْدِيهِمْ ۖ أَفَلَا يَشْكُرُونَ",
      "behavior_form": "inner_state",
      "agent": {
        "type": "AGT_BELIEVER",
        "explicit": false
      },
      "normative": {
        "speech_mode": "informative",
        "evaluation": "neutral",
        "deontic_signal": "khabar"
      },
      "action": {
        "class": "ACT_PSYCHOLOGICAL",
        "textual_eval": "EVAL_NEUTRAL"
      },
      "axes": {
        "situational": "internal",
        "systemic": "SYS_SOCIAL"
      },
      "evidence": {
        "support_type": "direct"
      },
      "annotator": "expert_scholar",
      "annotated_at": "2025-12-21T09:43:14.821538"
    }
  ]
}